app/__init__.py
app/__main__.py
app/filter.py
app/request.py
app/routes.py
app/version.py
app/models/__init__.py
app/models/config.py
app/models/endpoint.py
app/models/g_classes.py
app/services/__init__.py
app/services/cse_client.py
app/services/http_client.py
app/services/provider.py
app/static/bangs/00-whoogle.json
app/static/build/.gitignore
app/static/css/dark-theme.css
app/static/css/error.css
app/static/css/header.css
app/static/css/input.css
app/static/css/light-theme.css
app/static/css/logo.css
app/static/css/main.css
app/static/css/search.css
app/static/css/variables.css
app/static/img/favicon.ico
app/static/img/logo.png
app/static/img/whoogle.svg
app/static/img/favicon/android-icon-144x144.png
app/static/img/favicon/android-icon-192x192.png
app/static/img/favicon/android-icon-36x36.png
app/static/img/favicon/android-icon-48x48.png
app/static/img/favicon/android-icon-72x72.png
app/static/img/favicon/android-icon-96x96.png
app/static/img/favicon/apple-icon-114x114.png
app/static/img/favicon/apple-icon-120x120.png
app/static/img/favicon/apple-icon-144x144.png
app/static/img/favicon/apple-icon-152x152.png
app/static/img/favicon/apple-icon-180x180.png
app/static/img/favicon/apple-icon-57x57.png
app/static/img/favicon/apple-icon-60x60.png
app/static/img/favicon/apple-icon-72x72.png
app/static/img/favicon/apple-icon-76x76.png
app/static/img/favicon/apple-icon-precomposed.png
app/static/img/favicon/apple-icon.png
app/static/img/favicon/browserconfig.xml
app/static/img/favicon/favicon-16x16.png
app/static/img/favicon/favicon-32x32.png
app/static/img/favicon/favicon-96x96.png
app/static/img/favicon/favicon.ico
app/static/img/favicon/manifest.json
app/static/img/favicon/ms-icon-144x144.png
app/static/img/favicon/ms-icon-150x150.png
app/static/img/favicon/ms-icon-310x310.png
app/static/img/favicon/ms-icon-70x70.png
app/static/js/autocomplete.js
app/static/js/controller.js
app/static/js/currency.js
app/static/js/header.js
app/static/js/keyboard.js
whoogle_search-1.2.2.dist-info/licenses/LICENSE
whoogle_search-1.2.2.dist-info/METADATA
whoogle_search-1.2.2.dist-info/WHEEL
whoogle_search-1.2.2.dist-info/entry_points.txt
whoogle_search-1.2.2.dist-info/top_level.txt
whoogle_search-1.2.2.dist-info/RECORD
