Metadata-Version: 2.4
Name: whoogle-search
Version: 1.2.2
Summary: Self-hosted, ad-free, privacy-respecting metasearch engine
Home-page: https://github.com/benbusby/whoogle-search
Author: Ben Busby
Author-email: contact@benbusby.com
License: MIT
Keywords: search,metasearch,flask,adblock,degoogle,privacy
Classifier: Programming Language :: Python :: 3
Classifier: License :: OSI Approved :: MIT License
Classifier: Operating System :: OS Independent
License-File: LICENSE
Requires-Dist: beautifulsoup4
Requires-Dist: brotli
Requires-Dist: cssutils
Requires-Dist: cryptography
Requires-Dist: defusedxml
Requires-Dist: Flask
Requires-Dist: python-dotenv
Requires-Dist: httpx[http2,socks]
Requires-Dist: stem
Requires-Dist: validators
Requires-Dist: waitress
Provides-Extra: test
Requires-Dist: pytest; extra == "test"
Requires-Dist: python-dateutil; extra == "test"
Provides-Extra: dev
Requires-Dist: pycodestyle; extra == "dev"
Dynamic: license-file
